sshreader-6.2.0.dist-info/METADATA
sshreader-6.2.0.dist-info/WHEEL
sshreader-6.2.0.dist-info/entry_points.txt
sshreader-6.2.0.dist-info/licenses/LICENSE
sshreader-6.2.0.dist-info/licenses/LICENSE.lesser
sshreader/__init__.py
sshreader/customtypes.py
sshreader/scripts/__init__.py
sshreader/scripts/pydsh.py
sshreader/ssh.py
sshreader/utils.py
sshreader-6.2.0.dist-info/RECORD
