Metadata-Version: 2.1
Name: sshreader
Version: 6.2.0
Summary: Multi-threading/processing wrapper for Paramiko
Author-Email: Jesse Almanrode <jesse@almanrode.com>
License: LGPL-3.0-or-later
Classifier: Programming Language :: Python
Classifier: Intended Audience :: Developers
Classifier: License :: OSI Approved :: GNU Lesser General Public License v3 or later (LGPLv3+)
Classifier: Development Status :: 5 - Production/Stable
Classifier: Programming Language :: Python
Classifier: Programming Language :: Python :: 3.9
Classifier: Programming Language :: Python :: 3.10
Classifier: Programming Language :: Python :: 3.11
Classifier: Programming Language :: Python :: 3.12
Classifier: Programming Language :: Python :: 3.13
Classifier: Topic :: Software Development :: Libraries
Classifier: Topic :: Software Development :: Libraries :: Python Modules
Project-URL: homepage, http://sshreader.readthedocs.io/
Project-URL: repository, https://bitbucket.org/isaiah1112/sshreader/
Requires-Python: <4.0,>3.9
Requires-Dist: click<9,>=8
Requires-Dist: colorama<1.0,>=0.4
Requires-Dist: paramiko<4,>=3
Requires-Dist: progressbar2<5,>=4
Requires-Dist: python-hostlist<2,>=1
